fourier_grx_client-0.1.5.dist-info/METADATA
fourier_grx_client-0.1.5.dist-info/WHEEL
fourier_grx_client-0.1.5.dist-info/licenses/LICENSE
fourier_grx_client/__init__.py
fourier_grx_client/client.py
fourier_grx_client/constants.py
fourier_grx_client/exceptions.py
fourier_grx_client/utils.py
fourier_grx_client/zenoh_utils.py
fourier_grx_client-0.1.5.dist-info/RECORD
