Metadata-Version: 2.1
Name: fourier-grx-client
Version: 0.1.5
Summary: Client library for Fourier GRx series robots
Author-Email: Yuxiang Gao <yuxiang.gao@fftai.com>
License: MIT
Requires-Python: >=3.8
Requires-Dist: numpy>=1.24.4
Requires-Dist: msgpack>=1.0.8
Requires-Dist: msgpack-numpy>=0.4.8
Requires-Dist: eclipse-zenoh==0.11.0rc3
Requires-Dist: loguru>=0.7.2
Requires-Dist: rich>=13.8.0
